{
    "fluentMethods": true,
    "clientRootFolder": "",
    "relationships": [
        {
            "relationshipName": "sflUser",
            "otherEntityName": "sflUser",
            "relationshipType": "one-to-one",
            "otherEntityField": "id",
            "ownerSide": true,
            "useJPADerivedIdentifier": false,
            "otherEntityRelationshipName": "sflUserExtend"
        }
    ],
    "fields": [
        {
            "fieldName": "address",
            "fieldType": "String"
        }
    ],
    "changelogDate": "20210217161725",
    "dto": "mapstruct",
    "searchEngine": false,
    "service": "serviceImpl",
    "entityTableName": "sfl_user_extend",
    "databaseType": "sql",
    "readOnly": false,
    "jpaMetamodelFiltering": false,
    "pagination": "no"
}
